gemmology_plugin/__init__.py
gemmology_plugin/cli.py
gemmology_plugin/py.typed
gemmology_plugin-1.0.1.dist-info/licenses/LICENSE
gemmology_plugin-1.0.1.dist-info/METADATA
gemmology_plugin-1.0.1.dist-info/WHEEL
gemmology_plugin-1.0.1.dist-info/entry_points.txt
gemmology_plugin-1.0.1.dist-info/top_level.txt
gemmology_plugin-1.0.1.dist-info/RECORD
