Metadata-Version: 2.4
Name: gemmology-plugin
Version: 1.0.1
Summary: Claude Code plugin for coloured gemstone expertise and crystal visualization
Author-email: Fabian Schuh <fabian@gemmology.dev>
License: MIT
Project-URL: Homepage, https://gemmology.dev
Project-URL: Documentation, https://gemmology.dev/docs
Project-URL: Repository, https://github.com/gemmology-dev/gemmology-plugin
Project-URL: Issues, https://github.com/gemmology-dev/gemmology-plugin/issues
Keywords: gemmology,crystallography,gemstones,visualization,claude-code,plugin
Classifier: Development Status :: 5 - Production/Stable
Classifier: Intended Audience :: Science/Research
Classifier: License :: OSI Approved :: MIT License
Classifier: Operating System :: OS Independent
Classifier: Programming Language :: Python :: 3
Classifier: Programming Language :: Python :: 3.10
Classifier: Programming Language :: Python :: 3.11
Classifier: Programming Language :: Python :: 3.12
Classifier: Programming Language :: Python :: 3.13
Classifier: Topic :: Scientific/Engineering
Requires-Python: >=3.10
License-File: LICENSE
Requires-Dist: gemmology-cdl-parser>=1.0.0
Requires-Dist: gemmology-mineral-database>=1.0.0
Requires-Dist: gemmology-crystal-geometry>=1.0.0
Requires-Dist: gemmology-crystal-renderer>=1.0.0
Provides-Extra: dev
Requires-Dist: pytest>=7.0; extra == "dev"
Requires-Dist: pytest-cov>=4.0; extra == "dev"
Requires-Dist: ruff>=0.1.0; extra == "dev"
Requires-Dist: mypy>=1.0; extra == "dev"
Provides-Extra: lsp
Requires-Dist: gemmology-cdl-lsp>=1.0.0; extra == "lsp"
Provides-Extra: all
Requires-Dist: gemmology-cdl-lsp>=1.0.0; extra == "all"
Dynamic: license-file
